{
  "info": {
    "name": "watch",
    "description": "",
    "schema": "https://schema.getpostman.com/json/collection/v2.1.0/collection.json"
  },
  "item": [
    {
      "name": "bruno",
      "event": []
    },
    {
      "name": "Get watch",
      "event": [],
      "request": {
        "method": "GET",
        "header": [],
        "auth": {
          "type": "noauth"
        },
        "description": "",
        "url": {
          "raw": "http://127.0.0.1:8000/api/watch/1",
          "protocol": "http",
          "host": [
            "127",
            "0",
            "0",
            "1:8000"
          ],
          "path": [
            "api",
            "watch",
            "1"
          ],
          "query": [],
          "variable": []
        }
      }
    },
    {
      "name": "Delete watch",
      "event": [],
      "request": {
        "method": "DELETE",
        "header": [],
        "auth": {
          "type": "noauth"
        },
        "description": "",
        "url": {
          "raw": "http://127.0.0.1:8000/api/watch/2",
          "protocol": "http",
          "host": [
            "127",
            "0",
            "0",
            "1:8000"
          ],
          "path": [
            "api",
            "watch",
            "2"
          ],
          "query": [],
          "variable": []
        }
      }
    },
    {
      "name": "Create watch",
      "event": [],
      "request": {
        "method": "POST",
        "header": [],
        "auth": {
          "type": "noauth"
        },
        "description": "",
        "url": {
          "raw": "http://127.0.0.1:8000/api/watch",
          "protocol": "http",
          "host": [
            "127",
            "0",
            "0",
            "1:8000"
          ],
          "path": [
            "api",
            "watch"
          ],
          "query": [],
          "variable": []
        },
        "body": {
          "mode": "raw",
          "raw": "{\n    \"model\": \"watch33\",\n    \"brand\": \"casio\",\n    \"ean\": \"193456789\",\n    \"type_id\": \"3\",\n    \"strap_id\": \"1\",\n    \"year_edition\": \"2020\",\n    \"price\": 29.99\n}",
          "options": {
            "raw": {
              "language": "json"
            }
          }
        }
      }
    },
    {
      "name": "Get watches",
      "event": [],
      "request": {
        "method": "GET",
        "header": [],
        "auth": {
          "type": "noauth"
        },
        "description": "",
        "url": {
          "raw": "http://127.0.0.1:8000/api/watches",
          "protocol": "http",
          "host": [
            "127",
            "0",
            "0",
            "1:8000"
          ],
          "path": [
            "api",
            "watches"
          ],
          "query": [],
          "variable": []
        }
      }
    }
  ],
  "variable": []
}